biggo_pms_api_python/__init__.py
biggo_pms_api_python/error.py
biggo_pms_api_python/index.py
biggo_pms_api_python-1.1.1.dist-info/LICENSE
biggo_pms_api_python-1.1.1.dist-info/METADATA
biggo_pms_api_python-1.1.1.dist-info/WHEEL
biggo_pms_api_python-1.1.1.dist-info/top_level.txt
biggo_pms_api_python-1.1.1.dist-info/RECORD
