Metadata-Version: 2.1
Name: biggo-pms-api-python
Version: 1.1.1
Summary: UNKNOWN
Home-page: UNKNOWN
License: MIT
Platform: UNKNOWN
Requires: requests
Requires: base64
Requires: time
Requires: json
Requires: os
Requires: datetime
License-File: LICENSE
